[
  {
    "inputs": [
      {
        "internalType": "address",
        "name": "_originalContract",
        "type": "address"
      }
    ],
    "stateMutability": "nonpayable",
    "type": "constructor"
  },
  {
    "anonymous": false,
    "inputs": [
      {
        "indexed": true,
        "internalType": "uint256",
        "name": "originalTokenId",
        "type": "uint256"
      },
      {
        "indexed": true,
        "internalType": "address",
        "name": "creator",
        "type": "address"
      },
      {
        "indexed": false,
        "internalType": "address",
        "name": "collectibleContract",
        "type": "address"
      }
    ],
    "name": "ContentCreated",
    "type": "event"
  },
  {
    "inputs": [
      {
        "internalType": "string",
        "name": "title",
        "type": "string"
      },
      {
        "internalType": "string",
        "name": "genre",
        "type": "string"
      },
      {
        "internalType": "string",
        "name": "originalUri",
        "type": "string"
      },
      {
        "internalType": "string",
        "name": "collectibleUri",
        "type": "string"
      },
      {
        "internalType": "uint256",
        "name": "price",
        "type": "uint256"
      },
      {
        "internalType": "uint256",
        "name": "maxSupply",
        "type": "uint256"
      }
    ],
    "name": "createContent",
    "outputs": [
      {
        "internalType": "uint256",
        "name": "",
        "type": "uint256"
      },
      {
        "internalType": "address",
        "name": "",
        "type": "address"
      }
    ],
    "stateMutability": "nonpayable",
    "type": "function"
  },
  {
    "inputs": [],
    "name": "originalContract",
    "outputs": [
      {
        "internalType": "contract MVerOriginal",
        "name": "",
        "type": "address"
      }
    ],
    "stateMutability": "view",
    "type": "function"
  }
]
